{
  "cli": {
    "version": ">= 2.0.0"
  },
  "build": {
    "development": {
      "developmentClient": true,
      "distribution": "internal"
    },
    "preview": {
      "distribution": "internal"
    },
    "production": {
      "ios": {
        "resourceClass": "medium"
      },
      "android": {
        "resourceClass": "medium"
      }
    }
  },
  "submit": {
    "production": {
      "ios": {
        "appleId": "your-apple-id@email.com",
        "ascAppId": "your-app-store-connect-app-id",
        "appleTeamId": "your-team-id"
      },
      "android": {
        "serviceAccountKeyPath": "./path/to/api-key.json",
        "track": "internal"
      }
    },
    "preview": {
      "ios": {
        "appleId": "your-apple-id@email.com",
        "ascAppId": "your-app-store-connect-app-id",
        "appleTeamId": "your-team-id"
      }
    }
  }
}